{
  "name":"Desert Hell",
  "fog_color":"#ffffff",
  "triangle_colors": [
    "#3ba766",
    "#3caa7a",
    "#3cad8e",
    "#3cafa4",
    "#3caab2",
    "#3c99b5",
    "#3c86b8",
    "#3c73bb",
    "#3c5fbd"
  ],
  "triangle_color_bottom":"#892C0E",
  "base_floor":[{
    "stop" : 0,
    "value" : "#ffcc00"}
  ],
  "gradient_sun" : [
    {
      "stop" : 0,
      "value" : "#F5A43B"
    },
    {
      "stop" : 1,
      "value" : "#F5A43B"
    }
  ],
  "gradient_skybox": [
    {
      "stop" : 0,
      "value" :"#000000"
    },
    {
      "stop" : 0.45,
      "value" : "#000000"
    },
    {
      "stop" : 0.48,
      "value" : "#ADFF2F"
    },
    {
      "stop" : 1,
      "value" : "#FFE4C4"
    }
  ],
  "gradient_fogFloor" : [
    {
      "stop" : 0,
      "value" : "#FF4500"
    },
    {
      "stop" : 0.5,
      "value" : "#ff0000"
    },
    {
      "stop" : 1,
      "value" : "#FF4500"
    }
  ],
  "gradient_fogFloorAlpha" : [
    {
      "stop" : 0,
      "value" : "#000000"
    },
    {
      "stop" : 0.5,
      "value" : "#ffffff"
    },
    {
      "stop" : 0.8,
      "value" : "#000000"
    }
  ],
  "gradient_bg_front" : [
    {
      "stop" : 0,
      "value" : "#000000"
    },
    {
      "stop" : 0.5,
      "value" : "#000000"
    }
  ],
  "gradient_bg_back" : [
    {
      "stop" : 0,
      "value" : "#000000"
    },
    {
      "stop" : 1,
      "value" : "#000000"
    }
  ],
  "tex_floor" : "WhiteDesert",
  "tex_skybox" : null,
  "tex_bg_front" :"Black",
  "tex_bg_back" : "Black",
  "tex_guardian":"Grid",
  "tex_sun":"Black"
}